chatverse_moderation/__init__.py
chatverse_moderation-0.1.0.dist-info/licenses/LICENSE
chatverse_moderation-0.1.0.dist-info/METADATA
chatverse_moderation-0.1.0.dist-info/WHEEL
chatverse_moderation-0.1.0.dist-info/top_level.txt
chatverse_moderation-0.1.0.dist-info/RECORD
