Metadata-Version: 2.4
Name: chatverse_moderation
Version: 0.1.0
Summary: Custom library for sentiment analysis and content moderation in chat applications.
Home-page: https://github.com/yourusername/chatverse-moderation
Author: Hari Prasanna Kumar
Author-email: your.email@example.com
Classifier: Programming Language :: Python :: 3
Classifier: License :: OSI Approved :: MIT License
Requires-Python: >=3.6
License-File: LICENSE
Requires-Dist: textblob
Requires-Dist: nltk
Dynamic: author
Dynamic: author-email
Dynamic: classifier
Dynamic: description
Dynamic: description-content-type
Dynamic: home-page
Dynamic: license-file
Dynamic: requires-dist
Dynamic: requires-python
Dynamic: summary
